SKE/__init__.py
SKE/main.py
ske-0.1.1.dist-info/METADATA
ske-0.1.1.dist-info/WHEEL
ske-0.1.1.dist-info/entry_points.txt
ske-0.1.1.dist-info/top_level.txt
ske-0.1.1.dist-info/RECORD
