Metadata-Version: 2.4
Name: ske
Version: 0.1.1
Summary: Simple XOR file encryptor (.ske)
Author: sky
Requires-Python: >=3.8
Dynamic: author
Dynamic: description
Dynamic: description-content-type
Dynamic: requires-python
Dynamic: summary
